crypto_ai/__init__.py
crypto_ai-0.0.1.post1.dist-info/LICENSE
crypto_ai-0.0.1.post1.dist-info/METADATA
crypto_ai-0.0.1.post1.dist-info/WHEEL
crypto_ai-0.0.1.post1.dist-info/top_level.txt
crypto_ai-0.0.1.post1.dist-info/RECORD
