Metadata-Version: 2.1
Name: crypto-ai
Version: 0.0.1.post1
Summary: A simple Python SDK for Crypto AI API
Home-page: https://github.com/xk4rim/crypto-ai/
Author: k4rim
Author-email: xk4rim@gmail.com
Project-URL: Bug Tracker, https://github.com/xk4rim/crypto-ai/issues
Classifier: Programming Language :: Python :: 3
Classifier: License :: OSI Approved :: MIT License
Classifier: Operating System :: OS Independent
Requires-Python: >=3.6
License-File: LICENSE
Requires-Dist: requests
